test_marleen/__init__.py
test_marleen/myfunctions.py
test_marleen-0.0.2.dist-info/LICENSE.txt
test_marleen-0.0.2.dist-info/METADATA
test_marleen-0.0.2.dist-info/WHEEL
test_marleen-0.0.2.dist-info/top_level.txt
test_marleen-0.0.2.dist-info/RECORD
