Metadata-Version: 2.1
Name: test-marleen
Version: 0.0.2
Summary: Test the upload
Author: Marleen Maxton
License: X11
License-File: LICENSE.txt
